{ "compressionlevel":-1,
 "height":7,
 "infinite":false,
 "layers":[
        {
         "data":[0, 0, 0, 0, 0, 0, 0, 0, 0, 0, 0, 0, 0,
            0, 0, 0, 0, 0, 0, 0, 0, 0, 0, 0, 0, 0,
            0, 0, 0, 0, 0, 0, 0, 0, 0, 0, 0, 0, 0,
            0, 0, 0, 0, 0, 0, 0, 0, 0, 0, 0, 0, 0,
            0, 0, 0, 0, 0, 0, 0, 0, 0, 0, 0, 0, 0,
            0, 0, 0, 0, 0, 0, 0, 0, 0, 0, 0, 0, 0,
            0, 0, 0, 0, 0, 0, 0, 0, 0, 0, 0, 0, 0],
         "height":7,
         "id":1,
         "name":"Calque de Tuiles 1",
         "opacity":1,
         "type":"tilelayer",
         "visible":true,
         "width":13,
         "x":0,
         "y":0
        }, 
        {
         "id":2,
         "image":"Guest_Book_House_2.png",
         "name":"Calque d'Images 1",
         "opacity":1,
         "type":"imagelayer",
         "visible":true,
         "x":0,
         "y":0
        }, 
        {
         "draworder":"topdown",
         "id":3,
         "name":"Calque d'Objets 1",
         "objects":[
                {
                 "height":64,
                 "id":5,
                 "name":"",
                 "rotation":0,
                 "type":"",
                 "visible":true,
                 "width":176,
                 "x":16,
                 "y":16
                }, 
                {
                 "height":16,
                 "id":6,
                 "name":"",
                 "rotation":0,
                 "type":"",
                 "visible":true,
                 "width":80,
                 "x":16,
                 "y":80
                }, 
                {
                 "height":16,
                 "id":7,
                 "name":"",
                 "rotation":0,
                 "type":"",
                 "visible":true,
                 "width":80,
                 "x":112,
                 "y":80
                }, 
                {
                 "height":16,
                 "id":8,
                 "name":"",
                 "rotation":0,
                 "type":"",
                 "visible":true,
                 "width":16,
                 "x":192,
                 "y":96
                }, 
                {
                 "height":16,
                 "id":9,
                 "name":"",
                 "rotation":0,
                 "type":"",
                 "visible":true,
                 "width":16,
                 "x":192,
                 "y":0
                }, 
                {
                 "height":16,
                 "id":10,
                 "name":"",
                 "rotation":0,
                 "type":"",
                 "visible":true,
                 "width":16,
                 "x":0,
                 "y":0
                }, 
                {
                 "height":16,
                 "id":11,
                 "name":"",
                 "rotation":0,
                 "type":"",
                 "visible":true,
                 "width":16,
                 "x":0,
                 "y":96
                }],
         "opacity":1,
         "type":"objectgroup",
         "visible":true,
         "x":0,
         "y":0
        }],
 "nextlayerid":4,
 "nextobjectid":12,
 "orientation":"orthogonal",
 "renderorder":"right-down",
 "tiledversion":"1.11.0",
 "tileheight":16,
 "tilesets":[],
 "tilewidth":16,
 "type":"map",
 "version":"1.10",
 "width":13
}